LICENSE.md
README.md
setup.py
syndb.py
SynDB.egg-info/PKG-INFO
SynDB.egg-info/SOURCES.txt
SynDB.egg-info/dependency_links.txt
SynDB.egg-info/top_level.txt