Metadata-Version: 2.1
Name: SynDB
Version: 1.3
Summary: simple database using json.
Home-page: https://github.com/DeveloperJosh/SynDB
Author: Josh Wells
Author-email: bam0909@outlook.com
License: MIT
Platform: UNKNOWN
Classifier: Programming Language :: Python :: 3.7
Classifier: License :: OSI Approved :: MIT License
Classifier: Operating System :: OS Independent
